MANIFEST.in
README
build.bu
setup.py
Flask_FluidDB.egg-info/PKG-INFO
Flask_FluidDB.egg-info/SOURCES.txt
Flask_FluidDB.egg-info/dependency_links.txt
Flask_FluidDB.egg-info/namespace_packages.txt
Flask_FluidDB.egg-info/not-zip-safe
Flask_FluidDB.egg-info/requires.txt
Flask_FluidDB.egg-info/top_level.txt
docs/.index.rst.swp
docs/conf.py
docs/index.rst
docs/_themes/LICENSE
docs/_themes/README
docs/_themes/flask_theme_support.py
docs/_themes/flask_theme_support.pyc
docs/_themes/flask_small/layout.html
docs/_themes/flask_small/theme.conf
docs/_themes/flask_small/static/flasky.css_t
env/bin/activate_this.py
env/bin/rst2html.py
env/bin/rst2latex.py
env/bin/rst2man.py
env/bin/rst2newlatex.py
env/bin/rst2odt.py
env/bin/rst2odt_prepstyles.py
env/bin/rst2pseudoxml.py
env/bin/rst2s5.py
env/bin/rst2xml.py
env/bin/rstpep2html.py
env/lib/python2.6/UserDict.py
env/lib/python2.6/_abcoll.py
env/lib/python2.6/abc.py
env/lib/python2.6/codecs.py
env/lib/python2.6/copy_reg.py
env/lib/python2.6/fnmatch.py
env/lib/python2.6/genericpath.py
env/lib/python2.6/linecache.py
env/lib/python2.6/locale.py
env/lib/python2.6/ntpath.py
env/lib/python2.6/os.py
env/lib/python2.6/posixpath.py
env/lib/python2.6/re.py
env/lib/python2.6/site.py
env/lib/python2.6/sre.py
env/lib/python2.6/sre_compile.py
env/lib/python2.6/sre_constants.py
env/lib/python2.6/sre_parse.py
env/lib/python2.6/stat.py
env/lib/python2.6/types.py
env/lib/python2.6/warnings.py
env/lib/python2.6/distutils/__init__.py
env/lib/python2.6/site-packages/roman.py
env/lib/python2.6/site-packages/sphinx_pypi_upload.py
env/lib/python2.6/site-packages/Flask-0.6-py2.6.egg/flask/__init__.py
env/lib/python2.6/site-packages/Flask-0.6-py2.6.egg/flask/app.py
env/lib/python2.6/site-packages/Flask-0.6-py2.6.egg/flask/config.py
env/lib/python2.6/site-packages/Flask-0.6-py2.6.egg/flask/ctx.py
env/lib/python2.6/site-packages/Flask-0.6-py2.6.egg/flask/globals.py
env/lib/python2.6/site-packages/Flask-0.6-py2.6.egg/flask/helpers.py
env/lib/python2.6/site-packages/Flask-0.6-py2.6.egg/flask/logging.py
env/lib/python2.6/site-packages/Flask-0.6-py2.6.egg/flask/module.py
env/lib/python2.6/site-packages/Flask-0.6-py2.6.egg/flask/session.py
env/lib/python2.6/site-packages/Flask-0.6-py2.6.egg/flask/signals.py
